sender/__init__.py
sender/api/__init__.py
sender/api/sender_pb2.py
sender/api/sender_pb2_grpc.py
sender_service_Zulbukharov-0.0.3.dist-info/METADATA
sender_service_Zulbukharov-0.0.3.dist-info/WHEEL
sender_service_Zulbukharov-0.0.3.dist-info/top_level.txt
sender_service_Zulbukharov-0.0.3.dist-info/RECORD
